baseballdc/__init__.py
baseballdc/baseball_reference/__init__.py
baseballdc/baseball_reference/baseball_referenence_request_handler.py
baseballdc/baseball_reference/const/__init__.py
baseballdc/baseball_reference/const/baseball_reference_individual_player_tables_const.py
baseballdc/baseball_reference/const/baseball_reference_scope_const.py
baseballdc/baseball_reference/const/baseball_reference_season_tables_const.py
baseballdc/baseball_reference/const/baseball_reference_team_tables_const.py
baseballdc/baseball_reference/individual_player/__init__.py
baseballdc/baseball_reference/individual_player/baseball_reference_individual_player_request_handler.py
baseballdc/baseball_reference/individual_player/individual_player_identifier_service.py
baseballdc/baseball_reference/individual_player/individual_player_url_service.py
baseballdc/baseball_reference/season/__init__.py
baseballdc/baseball_reference/season/baseball_referenece_season_request_handler.py
baseballdc/baseball_reference/season/season_url_service.py
baseballdc/baseball_reference/shared/__init__.py
baseballdc/baseball_reference/shared/table_config_service.py
baseballdc/baseball_reference/shared/table_format_service.py
baseballdc/baseball_reference/shared/table_request_service.py
baseballdc/baseball_reference/team/__init__.py
baseballdc/baseball_reference/team/baseball_reference_team_request_handler.py
baseballdc/baseball_reference/team/team_url_service.py
baseballdc/const/__init__.py
baseballdc/const/data_source_const.py
baseballdc/request_validation/__init__.py
baseballdc/request_validation/request_validator.py
baseballdc-1.0.0.dist-info/LICENSE.txt
baseballdc-1.0.0.dist-info/METADATA
baseballdc-1.0.0.dist-info/WHEEL
baseballdc-1.0.0.dist-info/top_level.txt
baseballdc-1.0.0.dist-info/RECORD
