Metadata-Version: 2.1
Name: baseballdc
Version: 1.0.0
Summary: Baseball Data Center
Home-page: https://github.com/joesmi9/baseballdc
Author: Joe Smith
Author-email: joesmi9.sde@gmail.com
License: MIT
Keywords: baseball,baseball analytics,baseball reference,mlb
Platform: UNKNOWN
Classifier: Development Status :: 5 - Production/Stable
Classifier: Intended Audience :: Developers
Classifier: Programming Language :: Python :: 3
Classifier: Operating System :: Unix
Classifier: Operating System :: MacOS :: MacOS X
Classifier: Operating System :: Microsoft :: Windows
License-File: LICENSE.txt
